anprs/__init__.py
anprs/anprs.py
anprs/local_utils.py
media/photo.jpg
models/ocr_model.h5
models/wpod-net.json
models/wpod_net_all_in_one.h5
results/contour.jpg
results/res.jpg
anprs-0.0.6.dist-info/METADATA
anprs-0.0.6.dist-info/WHEEL
anprs-0.0.6.dist-info/top_level.txt
anprs-0.0.6.dist-info/RECORD
