Metadata-Version: 2.1
Name: anprs
Version: 0.0.6
Summary: Automatic Number Plate Recognition System
Home-page: https://github.com/Adityaupadhye/package_anprs
Author: Aditya Upadhye
Author-email: adityasu12@gmail.com
Requires-Python: >=3.6
Requires-Dist: opencv-python-headless
Requires-Dist: keras
Requires-Dist: tensorflow-cpu
